bigcode_astgen/__init__.py
bigcode_astgen/__main__.py
bigcode_astgen/ast_bulk_processor.py
bigcode_astgen/ast_generator.py
bigcode_astgen/cli.py
bigcode_astgen/glob.py
bigcode_astgen/normalizer.py
bigcode_astgen/queue_item.py
bigcode_astgen-0.2.1.data/scripts/bigcode-astgen-py
bigcode_astgen-0.2.1.dist-info/DESCRIPTION.rst
bigcode_astgen-0.2.1.dist-info/METADATA
bigcode_astgen-0.2.1.dist-info/RECORD
bigcode_astgen-0.2.1.dist-info/WHEEL
bigcode_astgen-0.2.1.dist-info/metadata.json
bigcode_astgen-0.2.1.dist-info/top_level.txt
bigcode_astgen-0.2.1.dist-info/zip-safe
