Metadata-Version: 1.1
Name: bigcode-astgen
Version: 0.2.1
Summary: Tool to search and fetch code from GitHub
Home-page: https://github.com/tuvistavie/bigcode-tools/tree/master/bigcode-astgen/python
Author: Daniel Perez
Author-email: tuvistavie@gmail.com
License: UNKNOWN
Download-URL: https://github.com/tuvistavie/bigcode-tools/archive/master.zip
Platform: UNKNOWN
Classifier: Development Status :: 4 - Beta
Classifier: Intended Audience :: Developers
Classifier: License :: OSI Approved :: MIT License
Classifier: Operating System :: OS Independent
Classifier: Programming Language :: Python :: 2
Classifier: Programming Language :: Python :: 3
